{
  "users": [
    {
      "Name": "cmd",
      "Address": "Mumbai",
      "Phno": "63524510",
      "Gender": "male",
      "Image": "http://p.imgci.com/db/PICTURES/CMS/128400/128483.1.jpg",
      "id": "2"
    },
    {
      "id": "3",
      "Name": "Rohit Sharma",
      "Address": "Mumbai",
      "Phno": "90239342",
      "Gender": "male",
      "Image": "https://i.pinimg.com/originals/54/8f/71/548f711858d49ed4adc5098b36dcbfee.jpg"
    },
    {
      "id": "4",
      "Name": "P V Sindhu",
      "Address": "Hyderabad",
      "Phno": "98723650",
      "Gender": "female",
      "Image": "https://images.news18.com/ibnlive/uploads/2016/10/PVSindhu-1.jpg"
    },
    {
      "id": "5",
      "Name": "Saina Nehwal",
      "Address": "Haryana",
      "Phno": "97453628",
      "Gender": "female",
      "Image": "https://upload.wikimedia.org/wikipedia/commons/thumb/7/70/Saina_Nehwal_in_2011.jpg/220px-Saina_Nehwal_in_2011.jpg"
    },
    {
      "Id": "6",
      "Name": "M S Dhoni",
      "Address": "Ranchi",
      "Phno": "875475236",
      "Gender": "male",
      "Image": "https://i.cricketcb.com/stats/img/faceImages/265.jpg",
      "id": "EP346gM"
    },
    {
      "Name": "Shreenil",
      "Address": "Ahmedabad",
      "Phno": 2133234,
      "Gender": "male",
      "Image": "https://pbs.twimg.com/profile_images/770254164471320576/x8tNo7NO.jpg",
      "id": "J4Tv75v"
    },
    {
      "Name": "M S Dhoni",
      "Address": "Ranchi",
      "Phno": "9",
      "Gender": "male",
      "Image": "https://i.cricketcb.com/stats/img/faceImages/265.jpg",
      "id": "ShhBmal"
    },
    {
      "Name": "Add Data",
      "Address": "Add Data",
      "Phno": "32234",
      "Gender": "male",
      "Image": "https://upload.wikimedia.org/wikipedia/commons/thumb/c/cf/Angular_full_color_logo.svg/1200px-Angular_full_color_logo.svg.png",
      "id": "jRhssYS"
    },
    {
      "Name": "name1563276064569",
      "Address": "Address",
      "Phno": "98835680",
      "Gender": "male",
      "Image": "https://i.cricketcb.com/stats/img/faceImages/265.jpg",
      "id": "xmsS3DE"
    },
    {
      "Name": "name1563276863170",
      "Address": "Address",
      "Phno": "98835680",
      "Gender": "male",
      "Image": "https://i.cricketcb.com/stats/img/faceImages/265.jpg",
      "id": "Nnnw-_l"
    },
    {
      "Name": "name1563355009583",
      "Address": "Address",
      "Phno": "98835680",
      "Gender": "male",
      "Image": "https://i.cricketcb.com/stats/img/faceImages/265.jpg",
      "id": "rm4aPLR"
    },
    {
      "Name": "name1563355386002",
      "Address": "Address",
      "Phno": "98835680",
      "Gender": "male",
      "Image": "https://i.cricketcb.com/stats/img/faceImages/265.jpg",
      "id": "jy9GukF"
    },
    {
      "Name": "name1563355553003",
      "Address": "Address",
      "Phno": "98835680",
      "Gender": "male",
      "Image": "https://i.cricketcb.com/stats/img/faceImages/265.jpg",
      "id": "3xJHUbq"
    },
    {
      "Name": "name1563355620600",
      "Address": "Address",
      "Phno": "98835680",
      "Gender": "male",
      "Image": "https://i.cricketcb.com/stats/img/faceImages/265.jpg",
      "id": "Nm55Orj"
    },
    {
      "Name": "name1563356137585",
      "Address": "Address",
      "Phno": "98835680",
      "Gender": "male",
      "Image": "https://i.cricketcb.com/stats/img/faceImages/265.jpg",
      "id": "rRwA7AN"
    },
    {
      "Name": "name1563356930228",
      "Address": "Address",
      "Phno": "98835680",
      "Gender": "male",
      "Image": "https://i.cricketcb.com/stats/img/faceImages/265.jpg",
      "id": "x5Z8iDe"
    },
    {
      "Name": "name1563358537200",
      "Address": "Address",
      "Phno": "98835680",
      "Gender": "male",
      "Image": "https://i.cricketcb.com/stats/img/faceImages/265.jpg",
      "id": "jfwQBUB"
    },
    {
      "Name": "name1563359186509",
      "Address": "Address",
      "Phno": "98835680",
      "Gender": "male",
      "Image": "https://i.cricketcb.com/stats/img/faceImages/265.jpg",
      "id": "LwQVCtD"
    }
  ]
}